{"classname": "FOOD", "metalabels": "+I+R+U-D"}
{"classname": "PIZZA NAME", "metalabels": "+I+R+U-D"}
{"classname": "MARGHERITA", "metalabels": "+I+R+U-D"}
{"classname": "MARINARA", "metalabels": "+I+R+U-D"}
{"classname": "QUATTRO FORMAGGI", "metalabels": "+I+R+U-D"}
{"classname": "PEPPERONI", "metalabels": "+I+R+U-D"}
{"classname": "NAPOLI DELIGHT", "metalabels": "+I+R+U-D"}
{"classname": "Hawaiian", "metalabels": "+I+R+U-D"}
{"classname": "PIZZA CRUST", "metalabels": "+I+R+U-D"}
{"classname": "NEAPOLITAN", "metalabels": "+I+R+U-D"}
{"classname": "FOCACCIA", "metalabels": "+I+R+U-D"}
{"classname": "SICILIAN", "metalabels": "+I+R+U-D"}
{"classname": "PIZZA TOPPING", "metalabels": "+I+R+U-D"}
{"classname": "SAUCE", "metalabels": "+I+R+U-D"}
{"classname": "TOMATO", "metalabels": "+I+R+U-D"}
{"classname": "PESTO", "metalabels": "+I+R+U-D"}
{"classname": "CHEESE", "metalabels": "+I+R+U-D"}
{"classname": "MOZZARELLA", "metalabels": "+I+R+U-D"}
{"classname": "PARMESAN", "metalabels": "+I+R+U-D"}
{"classname": "VEG", "metalabels": "+I+R+U-D"}
{"classname": "MUSHROOM", "metalabels": "+I+R+U-D"}
{"classname": "ONION", "metalabels": "+I+R+U-D"}
{"classname": "MEAT", "metalabels": "+I+R+U-D"}
{"classname": "BEEF", "metalabels": "+I+R+U-D"}
{"classname": "CHICKEN", "metalabels": "+I+R+U-D"}
